wimbd/es/__init__.py
wimbd/es/corpus_contamination.py
wimbd/es/random_access.py
wimbd-0.1.1.dist-info/LICENSE
wimbd-0.1.1.dist-info/METADATA
wimbd-0.1.1.dist-info/WHEEL
wimbd-0.1.1.dist-info/top_level.txt
wimbd-0.1.1.dist-info/RECORD
