Metadata-Version: 2.1
Name: wimbd
Version: 0.1.1
Summary: An elasticsearch wrapper that allows to query ES indices
Home-page: https://wimbd.apps.allenai.org/
Author: Yanai Elazar, Akshita Bhagia, Ian Magnusson, Abhilasha Ravichander, Dustin Schwenk, Alane Suhr, Pete Walsh, Dirk Groeneveld, Luca Soldaini, Sameer Singh, Hanna Hajishirzi, Noah A. Smith, Jesse Dodge
Author-email: yanaiela@gmail.com
Classifier: Programming Language :: Python :: 3
Classifier: License :: OSI Approved :: Apache Software License
Classifier: Operating System :: OS Independent
Requires-Python: >=3.9
License-File: LICENSE
Requires-Dist: elasticsearch (>=8.6.2)
Requires-Dist: pyyaml
